asyncimg/__init__.py
asyncimg/_generator.py
asyncimg/_util.py
asyncimg/assets/envelop.png
asyncimg/assets/fart.jpeg
asyncimg/assets/font.ttf
asyncimg/assets/frame.png
asyncimg/assets/ko.jpeg
asyncimg/assets/love.png
asyncimg/assets/profile.jpg
asyncimg/assets/stars.png
asyncimg-1.0.1.dist-info/LICENSE
asyncimg-1.0.1.dist-info/METADATA
asyncimg-1.0.1.dist-info/WHEEL
asyncimg-1.0.1.dist-info/top_level.txt
asyncimg-1.0.1.dist-info/RECORD
