Metadata-Version: 2.1
Name: asyncimg
Version: 1.0.1
Summary: An async image manipulation lib. Can be used for discord.
Home-page: https://github.com/shahprog/asyncimg/
Author: Md Shahriyar Alam
Author-email: mdshahriyaralam552@gmail.com
License: MIT
Keywords: discord discord-rank discord-profile discord-leveling
Platform: UNKNOWN
Classifier: Development Status :: 5 - Production/Stable
Classifier: Intended Audience :: Education
Classifier: Operating System :: POSIX :: Linux
Classifier: Operating System :: Microsoft :: Windows
Classifier: Operating System :: MacOS
Classifier: License :: OSI Approved :: MIT License
Classifier: Programming Language :: Python :: 3
Requires-Dist: Pillow
Requires-Dist: aiohttp
Requires-Dist: colorthief
